[
  {
    "id": 1,
    "title": "Гамлет",
    "author": "Уильям Шекспир",
    "genre": "Трагедия",
    "duration": 180,
    "premiereDate": "2024-10-15",
    "isActive": true,
    "actors": ["Иван Петров", "Мария Сидорова", "Алексей Иванов"],
    "price": 1500
  },
  {
    "id": 2,
    "title": "Ревизор",
    "author": "Николай Гоголь",
    "genre": "Комедия",
    "duration": 120,
    "premiereDate": "2024-11-20",
    "isActive": true,
    "actors": ["Петр Сергеев", "Ольга Кузнецова"],
    "price": 1200
  },
  {
    "id": 3,
    "title": "Чайка",
    "author": "Антон Чехов",
    "genre": "Драма",
    "duration": 140,
    "premiereDate": "2024-09-10",
    "isActive": false,
    "actors": ["Сергей Волков", "Елена Морозова", "Дмитрий Соколов"],
    "price": 1100
  },
  {
    "id": 4,
    "title": "Лебединое озеро",
    "author": "Петр Чайковский",
    "genre": "Балет",
    "duration": 130,
    "premiereDate": "2024-12-25",
    "isActive": true,
    "actors": ["Анна Смирнова", "Михаил Орлов", "Татьяна Ковалева"],
    "price": 2000
  }
]